LICENSE
README.md
setup.py
tkWidgetsRfzorzi/__init__.py
tkWidgetsRfzorzi/setup.py
tkWidgetsRfzorzi/widgets_Glac.py
tkWidgetsRfzorzi.egg-info/PKG-INFO
tkWidgetsRfzorzi.egg-info/SOURCES.txt
tkWidgetsRfzorzi.egg-info/dependency_links.txt
tkWidgetsRfzorzi.egg-info/requires.txt
tkWidgetsRfzorzi.egg-info/top_level.txt