Metadata-Version: 2.1
Name: tkWidgetsRfzorzi
Version: 0.1.4
Summary: Modulo que adiciona recursos extras ao tkinter
Home-page: https://github.com/rafael-rfzorzi/estiloWidgets
Author: Rafael De Leon Serafim
Author-email: rafaelserafim.rfzorzi@gmail.com
License: MIT License
Keywords: autocomplety buttonStyle entryPlaceHolder gradienteFrame labelStyle
License-File: LICENSE
